KapianBijiXiezuofa/README.md
KapianBijiXiezuofa/__init__.py
KapianBijiXiezuofa/__main__.py
KapianBijiXiezuofa/file.epub
KapianBijiXiezuofa/index.html
KapianBijiXiezuofa/css/__init__.py
KapianBijiXiezuofa/css/annotations.css
KapianBijiXiezuofa/css/main.css
KapianBijiXiezuofa/css/normalize.css
KapianBijiXiezuofa/css/popup.css
KapianBijiXiezuofa/font/__init__.py
KapianBijiXiezuofa/font/fontello.eot
KapianBijiXiezuofa/font/fontello.svg
KapianBijiXiezuofa/font/fontello.ttf
KapianBijiXiezuofa/font/fontello.woff
KapianBijiXiezuofa/img/__init__.py
KapianBijiXiezuofa/img/annotator-glyph-sprite.png
KapianBijiXiezuofa/img/annotator-icon-sprite.png
KapianBijiXiezuofa/img/apple-touch-icon.png
KapianBijiXiezuofa/img/cancelfullscreen.png
KapianBijiXiezuofa/img/close.png
KapianBijiXiezuofa/img/fullscreen.png
KapianBijiXiezuofa/img/loader.gif
KapianBijiXiezuofa/img/menu-icon.png
KapianBijiXiezuofa/img/save.png
KapianBijiXiezuofa/img/saved.png
KapianBijiXiezuofa/img/settings-s.png
KapianBijiXiezuofa/img/settings.png
KapianBijiXiezuofa/img/star.png
KapianBijiXiezuofa/js/__init__.py
KapianBijiXiezuofa/js/epub.js
KapianBijiXiezuofa/js/epub.min.js
KapianBijiXiezuofa/js/epub.min.map
KapianBijiXiezuofa/js/hooks.min.js
KapianBijiXiezuofa/js/hooks.min.map
KapianBijiXiezuofa/js/reader.js
KapianBijiXiezuofa/js/reader.js.map
KapianBijiXiezuofa/js/reader.min.js
KapianBijiXiezuofa/js/reader.min.map
KapianBijiXiezuofa/js/hooks/__init__.py
KapianBijiXiezuofa/js/hooks/extensions/__init__.py
KapianBijiXiezuofa/js/hooks/extensions/highlight.js
KapianBijiXiezuofa/js/libs/__init__.py
KapianBijiXiezuofa/js/libs/jquery.min.js
KapianBijiXiezuofa/js/libs/localforage.min.js
KapianBijiXiezuofa/js/libs/screenfull.js
KapianBijiXiezuofa/js/libs/screenfull.min.js
KapianBijiXiezuofa/js/libs/zip.min.js
KapianBijiXiezuofa/js/plugins/__init__.py
KapianBijiXiezuofa/js/plugins/hypothesis.js
KapianBijiXiezuofa/js/plugins/search.js
kapian_biji_xiezuofa-2022.10.15.0.dist-info/METADATA
kapian_biji_xiezuofa-2022.10.15.0.dist-info/WHEEL
kapian_biji_xiezuofa-2022.10.15.0.dist-info/entry_points.txt
kapian_biji_xiezuofa-2022.10.15.0.dist-info/top_level.txt
kapian_biji_xiezuofa-2022.10.15.0.dist-info/RECORD
